{
  "quests": 
  [
    {
      "questId": 2000,
      "questNpcId": 1000,
      "questName": "Quest_Name_1",
      "goal": "Quest_Goal_1",
      "content": "Quest_Content_1",
      "nextQuestId": 2001,
      "startDialogues": [ "Quest_Dialogue_1", "Quest_Dialogue_2" ],
      "progressingDialogues": [ "Quest_Dialogue_2"],
      "endDialogues": [ "Quest_Dialogue_3", "Quest_Dialogue_4" ],
      "task": {
        "collect": [200, 1],
        "kill": []
      },
      "reward": {
        "exp": 100,
        "gold": 200,
        "items": [
          {
            "itemId": 0,
            "itemCount": -1
          }
        ]
      }
    },

    {
      "questId": 2001,
      "questNpcId": 1001,
      "questName": "Quest_Name_2",
      "goal": "Quest_Goal_2",
      "content": "Quest_Content_2",
      "nextQuestId": -1,
      "startDialogues": [ "Quest_Dialogue_5", "Quest_Dialogue_6" ],
      "progressingDialogues": [ "Quest_Dialogue_6" ],
      "endDialogues": [ "Quest_Dialogue_7", "Quest_Dialogue_8" ],
      "task": {
        "collect": [201, 1],
        "kill": []
      },
      "reward": {
        "exp": 200,
        "gold": 400,
        "items": [
          {
            "itemId": 100,
            "itemCount": 3
          }
        ]
      }
    }    
  ]
}